jqk/__init__.py
jqk/__main__.py
jqkey-0.1.dist-info/LICENSE
jqkey-0.1.dist-info/METADATA
jqkey-0.1.dist-info/WHEEL
jqkey-0.1.dist-info/entry_points.txt
jqkey-0.1.dist-info/top_level.txt
jqkey-0.1.dist-info/RECORD
